iskalko_otzyvy_ru/__init__.py
iskalko_otzyvy_ru/iskalko_otzyvy_ru.py
iskalko_otzyvy_ru-0.1.2.dist-info/LICENSE
iskalko_otzyvy_ru-0.1.2.dist-info/METADATA
iskalko_otzyvy_ru-0.1.2.dist-info/WHEEL
iskalko_otzyvy_ru-0.1.2.dist-info/top_level.txt
iskalko_otzyvy_ru-0.1.2.dist-info/RECORD
