Metadata-Version: 2.1
Name: iskalko-otzyvy-ru
Version: 0.1.2
Summary: iskalko_otzyvy_ru reviews site
Home-page: https://github.com/NMelis/iskalko_otzyvy_ru
Author: Melis Nurlan
Author-email: melis.zhoroev@gmail.com
License: MIT license
Keywords: iskalko_otzyvy_ru
Platform: UNKNOWN
Classifier: Development Status :: 2 - Pre-Alpha
Classifier: Intended Audience :: Developers
Classifier: License :: OSI Approved :: MIT License
Classifier: Natural Language :: English
Classifier: Programming Language :: Python :: 2
Classifier: Programming Language :: Python :: 2.7
Classifier: Programming Language :: Python :: 3
Classifier: Programming Language :: Python :: 3.4
Classifier: Programming Language :: Python :: 3.5
Classifier: Programming Language :: Python :: 3.6
Classifier: Programming Language :: Python :: 3.7
Requires-Dist: requests
